Metadata-Version: 2.1
Name: onefx
Version: 0.0.3
Summary: A toolkit for developers to simplify the transformation of nn.Module instances.
Home-page: UNKNOWN
Author: OneFlow
Author-email: 
License: Apache 2.0
Platform: UNKNOWN
Classifier: Programming Language :: Python :: 3
Classifier: License :: OSI Approved :: Apache Software License
Classifier: Operating System :: OS Independent
